palavreco/db.json
palavreco/dueto.py
palavreco/main.py
palavreco/termo.py
palavreco/utils.py
palavreco-0.1.2.dist-info/METADATA
palavreco-0.1.2.dist-info/WHEEL
palavreco-0.1.2.dist-info/entry_points.txt
palavreco-0.1.2.dist-info/RECORD
