Metadata-Version: 2.1
Name: palavreco
Version: 0.1.2
Summary: Palavreco é um jogo para terminal baseado no Wordle, Termo e Letreco.
Author: gbPagano
Author-email: guilhermebpagano@gmail.com
Requires-Python: >=3.11,<4.0
Classifier: Programming Language :: Python :: 3
Classifier: Programming Language :: Python :: 3.11
Requires-Dist: rich (>=13.5.2,<14.0.0)
Requires-Dist: rich-menu (>=0.1.3,<0.2.0)
Requires-Dist: textual (>=0.35.1,<0.36.0)
Requires-Dist: tinydb (>=4.8.0,<5.0.0)
